custom_rap_installer/__about__.py
custom_rap_installer/__init__.py
custom_rap_installer/__main__.py
custom_rap_installer/pictorymanager.py
custom_rap_installer-0.0.1.dist-info/GPL-2.0-or-later.txt
custom_rap_installer-0.0.1.dist-info/METADATA
custom_rap_installer-0.0.1.dist-info/WHEEL
custom_rap_installer-0.0.1.dist-info/top_level.txt
custom_rap_installer-0.0.1.dist-info/RECORD
