Metadata-Version: 2.1
Name: custom_rap_installer
Version: 0.0.1
Summary: Install custom RAP files for use in PiCtory
Home-page: https://revolutionpi.com/
Author: Sven Sager
Author-email: s.sager@kunbus.com
Maintainer: KUNBUS GmbH
Maintainer-email: support@kunbus.com
License: GPL-2.0-or-later
Keywords: revpi,revolution pi,pictory
Platform: revolution pi
Classifier: Development Status :: 4 - Beta
Classifier: Intended Audience :: Developers
Classifier: License :: OSI Approved :: GNU General Public License v2 or later (GPLv2+)
Classifier: Operating System :: POSIX
Classifier: Programming Language :: Python
Classifier: Topic :: Software Development :: Libraries :: Python Modules
Requires-Python: >= 3.7
License-File: LICENSES/GPL-2.0-or-later.txt
